bilby_pipe/__init__.py
bilby_pipe/_version.py
bilby_pipe/bilbyargparser.py
bilby_pipe/create_injections.py
bilby_pipe/data_analysis.py
bilby_pipe/data_generation.py
bilby_pipe/gracedb.py
bilby_pipe/htcondor_sync.py
bilby_pipe/input.py
bilby_pipe/ligo_skymap.py
bilby_pipe/main.py
bilby_pipe/parser.py
bilby_pipe/plot.py
bilby_pipe/plotting_utils.py
bilby_pipe/pp_test.py
bilby_pipe/process_bilby_mcmc.py
bilby_pipe/review.py
bilby_pipe/utils.py
bilby_pipe/xml_converter.py
bilby_pipe/asimov/__init__.py
bilby_pipe/asimov/asimov.py
bilby_pipe/asimov/config.ini
bilby_pipe/asimov/online.py
bilby_pipe/asimov/online_config.ini
bilby_pipe/data_files/128s.prior
bilby_pipe/data_files/128s_distance_marginalization_lookup.npz
bilby_pipe/data_files/128s_distance_marginalization_lookup_phase.npz
bilby_pipe/data_files/128s_tidal.prior
bilby_pipe/data_files/128s_tidal_distance_marginalization_lookup.npz
bilby_pipe/data_files/128s_tidal_distance_marginalization_lookup_phase.npz
bilby_pipe/data_files/128s_tidal_lowspin.prior
bilby_pipe/data_files/128s_tidal_lowspin_distance_marginalization_lookup.npz
bilby_pipe/data_files/128s_tidal_lowspin_distance_marginalization_lookup_phase.npz
bilby_pipe/data_files/16s.prior
bilby_pipe/data_files/16s_distance_marginalization_lookup.npz
bilby_pipe/data_files/16s_distance_marginalization_lookup_phase.npz
bilby_pipe/data_files/32s.prior
bilby_pipe/data_files/32s_distance_marginalization_lookup.npz
bilby_pipe/data_files/32s_distance_marginalization_lookup_phase.npz
bilby_pipe/data_files/4s.prior
bilby_pipe/data_files/4s_distance_marginalization_lookup.npz
bilby_pipe/data_files/4s_distance_marginalization_lookup_phase.npz
bilby_pipe/data_files/64s.prior
bilby_pipe/data_files/64s_distance_marginalization_lookup.npz
bilby_pipe/data_files/64s_distance_marginalization_lookup_phase.npz
bilby_pipe/data_files/8s.prior
bilby_pipe/data_files/8s_distance_marginalization_lookup.npz
bilby_pipe/data_files/8s_distance_marginalization_lookup_phase.npz
bilby_pipe-1.8.0.dist-info/licenses/LICENSE
bilby_pipe-1.8.0.dist-info/METADATA
bilby_pipe-1.8.0.dist-info/WHEEL
bilby_pipe-1.8.0.dist-info/entry_points.txt
bilby_pipe-1.8.0.dist-info/top_level.txt
bilby_pipe-1.8.0.dist-info/RECORD
